yors_comfyui_node_as_x_type/__init__.py
yors_comfyui_node_as_x_type/main.py
yors_comfyui_node_as_x_type-0.2.1.dist-info/METADATA
yors_comfyui_node_as_x_type-0.2.1.dist-info/WHEEL
yors_comfyui_node_as_x_type-0.2.1.dist-info/RECORD
