Metadata-Version: 2.1
Name: yors_comfyui_node_as_x_type
Version: 0.2.1
Summary: some comfyui custom nodes to set it as known type
Home-page: https://github.com//blob/main/packages/yors_comfyui_node_as_x_type/README.md
License: LICENSE
Keywords: artist,panz,mono,yors_comfyui_node_as_x_type
Author: yemiancheng
Author-email: ymc.github@gmail.com
Requires-Python: >=3.10,<4.0
Classifier: Development Status :: 3 - Alpha
Classifier: Intended Audience :: Developers
Classifier: License :: OSI Approved :: MIT License
Classifier: License :: Other/Proprietary License
Classifier: Programming Language :: Python :: 3
Classifier: Programming Language :: Python :: 3.10
Classifier: Programming Language :: Python :: 3.11
Classifier: Programming Language :: Python :: 3.12
Classifier: Topic :: Software Development :: Build Tools
Project-URL: Documentation, https://github.com//blob/main/packages/yors_comfyui_node_as_x_type/README.md
Project-URL: Repository, https://github.com/.git
Project-URL: changelog, https://github.com//blob/main/packages/yors_comfyui_node_as_x_type/CHANGELOG.md
